IVA_EXP_29/__init__.py
IVA_EXP_29/exp1.py
IVA_EXP_29/exp2.py
IVA_EXP_29/exp3.py
IVA_EXP_29/exp4.py
IVA_EXP_29/exp5.py
IVA_EXP_29/exp6.py
IVA_EXP_29/main.py
IVA_EXP_29-0.1.0.dist-info/METADATA
IVA_EXP_29-0.1.0.dist-info/WHEEL
IVA_EXP_29-0.1.0.dist-info/top_level.txt
IVA_EXP_29-0.1.0.dist-info/RECORD
